bifacial_radiance_local/__init__.py
bifacial_radiance_local/setAnalysisObj.py
bifacial_radiance_local/setModules.py
bifacial_radiance_local/setScene.py
bifacial_radiance_local/setSkyDome.py
bifacial_radiance_local/setWeather.py
rayoptix/__init__.py
rayoptix/main.py
tests/__init__.py
utils/__init__.py
utils/csv_folder_utils.py
utils/folders_utils.py
utils/json_folder_utils.py
utils/metadata_utils.py
utils/metrics_utils.py
utils/modules_utils.py
utils/scene_utils.py
utils/setup_folders.py
rayoptix-1.0.2.dist-info/LICENSE
rayoptix-1.0.2.dist-info/METADATA
rayoptix-1.0.2.dist-info/WHEEL
rayoptix-1.0.2.dist-info/entry_points.txt
rayoptix-1.0.2.dist-info/top_level.txt
rayoptix-1.0.2.dist-info/RECORD
