Metadata-Version: 2.1
Name: rayoptix
Version: 1.0.2
Summary: Rayoptix is a terminal-based Python library for creating and evaluating simulations of bifacial photovoltaic systems using ray tracing. It allows users to define modules, configure experimental conditions, and analyze energy performance in complex solar setups.
Home-page: https://github.com/Daval03/CE-114-rayoptix
Author: Aldo Cambronero Ureña
Author-email: cambroneroaldo03@gmail.com
Classifier: Programming Language :: Python :: 3
Classifier: License :: OSI Approved :: MIT License
Classifier: Operating System :: Microsoft :: Windows
Classifier: Operating System :: POSIX :: Linux
Requires-Python: >=3.6
License-File: LICENSE
Requires-Dist: bifacial-radiance
Requires-Dist: pandas
Requires-Dist: matplotlib
Requires-Dist: sutil
Requires-Dist: GPUtil
Requires-Dist: seaborn
Requires-Dist: psutil
